{
  "timestamp": "2025-10-19T20:55:54+03:00",
  "build": {
    "build_success": true,
    "vet_warnings": 0,
    "lint_warnings": 3,
    "tests_pass": true,
    "coverage_pct": 53.3,
    "cyclomatic_avg": 1.5217391304347827,
    "gen_time_sec": 1.012784896,
    "timestamp": "2025-10-19T20:55:54+03:00"
  },
  "generation": {
    "StartTime": "2025-10-19T20:54:35.616317139+03:00",
    "EndTime": "2025-10-19T20:55:53.912078782+03:00",
    "Duration": 78295761643,
    "PrimarySuccess": false,
    "RepairAttempts": 1,
    "FinalSuccess": true,
    "ErrorMessage": "",
    "RuleFixes": 25
  }
}