{
  "timestamp": "2025-10-22T04:19:11+03:00",
  "build": {
    "build_success": true,
    "vet_warnings": 1,
    "lint_warnings": 7,
    "tests_pass": false,
    "coverage_pct": 0,
    "cyclomatic_avg": 2.75,
    "gen_time_sec": 0.944683086,
    "timestamp": "2025-10-22T04:19:11+03:00"
  },
  "generation": {
    "StartTime": "2025-10-22T04:18:47.026453278+03:00",
    "EndTime": "2025-10-22T04:19:10.24300767+03:00",
    "Duration": 23216554400,
    "PrimarySuccess": true,
    "RepairAttempts": 0,
    "FinalSuccess": true,
    "ErrorMessage": "",
    "RuleFixes": 11,
    "Mode": "ml"
  }
}