{
  "timestamp": "2025-10-22T07:54:14+03:00",
  "build": {
    "build_success": true,
    "vet_warnings": 0,
    "lint_warnings": 3,
    "tests_pass": true,
    "coverage_pct": 70.2,
    "cyclomatic_avg": 2.96875,
    "gen_time_sec": 1.317526944,
    "timestamp": "2025-10-22T07:54:14+03:00"
  },
  "generation": {
    "StartTime": "2025-10-22T07:53:07.850824382+03:00",
    "EndTime": "2025-10-22T07:54:12.722819234+03:00",
    "Duration": 64871994861,
    "PrimarySuccess": true,
    "RepairAttempts": 0,
    "FinalSuccess": true,
    "ErrorMessage": "",
    "RuleFixes": 26,
    "Mode": "hybrid"
  }
}