{
  "timestamp": "2025-10-20T03:23:48+03:00",
  "build": {
    "build_success": true,
    "vet_warnings": 0,
    "lint_warnings": 3,
    "tests_pass": true,
    "coverage_pct": 53.3,
    "cyclomatic_avg": 1.5217391304347827,
    "gen_time_sec": 0.938269938,
    "timestamp": "2025-10-20T03:23:48+03:00"
  },
  "generation": {
    "StartTime": "2025-10-20T03:23:14.542069141+03:00",
    "EndTime": "2025-10-20T03:23:47.056394847+03:00",
    "Duration": 32514325774,
    "PrimarySuccess": true,
    "RepairAttempts": 0,
    "FinalSuccess": true,
    "ErrorMessage": "",
    "RuleFixes": 25
  }
}