{
  "timestamp": "2025-10-19T21:36:28+03:00",
  "build": {
    "build_success": true,
    "vet_warnings": 0,
    "lint_warnings": 0,
    "tests_pass": true,
    "coverage_pct": 72.2,
    "cyclomatic_avg": 3.0625,
    "gen_time_sec": 0.882567591,
    "timestamp": "2025-10-19T21:36:28+03:00"
  },
  "generation": {
    "StartTime": "2025-10-19T21:36:27.729585184+03:00",
    "EndTime": "2025-10-19T21:36:27.72972246+03:00",
    "Duration": 137280,
    "PrimarySuccess": true,
    "RepairAttempts": 1,
    "FinalSuccess": true,
    "ErrorMessage": "failed to parse repaired output: json parse error: invalid character 'e' after object key:value pair",
    "RuleFixes": 11
  }
}