{
  "timestamp": "2025-10-21T20:09:59+03:00",
  "build": {
    "build_success": false,
    "vet_warnings": 2,
    "lint_warnings": 0,
    "tests_pass": false,
    "coverage_pct": 0,
    "cyclomatic_avg": 3.129032258064516,
    "gen_time_sec": 0.616277175,
    "timestamp": "2025-10-21T20:09:59+03:00"
  },
  "generation": {
    "StartTime": "2025-10-21T20:09:58.662876567+03:00",
    "EndTime": "2025-10-21T20:09:58.695375512+03:00",
    "Duration": 32498944,
    "PrimarySuccess": true,
    "RepairAttempts": 0,
    "FinalSuccess": true,
    "ErrorMessage": "",
    "RuleFixes": 11,
    "Mode": "rules"
  }
}